{
  "PSR-36": {
    "00": "Brass 2",
    "01": "Horn",
    "02": "Flute",
    "03": "Clarinet",
    "04": "Strings",
    "05": "Jazz Organ",
    "06": "Pipe Organ 2",
    "07": "Cosmic",
    "08": "Pop Synth",
    "09": "Funk Synth",
    "10": "Percus 2",
    "11": "Piano",
    "12": "Harpsichord",
    "13": "Jazz Guitar",
    "14": "Vibes",
    "15": "Bells",
    "16": "Brass 1",
    "17": "Sax",
    "18": "Wah Brass",
    "19": "Oboe",
    "20": "Cello",
    "21": "Synth Organ",
    "22": "Pipe Organ 1",
    "23": "Fantasy",
    "24": "Blues Synth",
    "25": "Slap Synth",
    "26": "Percus 1",
    "27": "Elec. Piano",
    "28": "Banjo",
    "29": "Elec. Guitar",
    "30": "Music Box",
    "31": "Koto"
  },
  "POGOLAB": {
    "00": "Acoustic Grand Piano",
    "01": "Bright Acoustic Piano",
    "02": "Electric Grand Piano",
    "03": "Honky-Tonk Piano",
    "04": "Electric Piano 1",
    "05": "Electric Piano 2",
    "06": "Harpsichord",
    "07": "Clavichord",
    "08": "Celesta",
    "09": "Glockenspiel",
    "10": "Music Box",
    "11": "Vibraphone",
    "12": "Marimba",
    "13": "Xylophone",
    "14": "Tubular Bells",
    "15": "Dulcimer",
    "16": "Drawbar Organ",
    "17": "Percussive Organ",
    "18": "Rock Organ",
    "19": "Church Organ",
    "20": "Reed Organ",
    "21": "Accordion",
    "22": "Harmonica",
    "23": "Tango Accordion",
    "24": "Acoustic Guitar (nylon)",
    "25": "Acoustic Guitar (steel)",
    "26": "Electric Guitar (jazz)",
    "27": "Electric Guitar (clean)",
    "28": "Electric Guitar (muted)",
    "29": "Overdriven Guitar",
    "30": "Distortion Guitar",
    "31": "Guitar Harmonics",
    "32": "Acoustic Bass",
    "33": "Electric Bass (finger)",
    "34": "Electric Bass (pick)",
    "35": "Fretless Bass",
    "36": "Slap Bass 1",
    "37": "Slap Bass 2",
    "38": "Synth Bass 1",
    "39": "Synth Bass 2",
    "40": "Violin",
    "41": "Viola",
    "42": "Cello",
    "43": "Contrabass",
    "44": "Tremolo Strings",
    "45": "Pizzicato Strings",
    "46": "Orchestral Harp",
    "47": "Timpani",
    "48": "String Ensemble 1",
    "49": "String Ensemble 2",
    "50": "Synth Strings 1",
    "51": "Synth Strings 2",
    "52": "Choir Aahs",
    "53": "Voice Oohs",
    "54": "Synth Voice",
    "55": "Orchestra Hit",
    "56": "Trumpet",
    "57": "Trombone",
    "58": "Tuba",
    "59": "Muted Trumpet",
    "60": "French Horn",
    "61": "Brass Section",
    "62": "Synth Brass 1",
    "63": "Synth Brass 2",
    "64": "Soprano Sax",
    "65": "Alto Sax",
    "66": "Tenor Sax",
    "67": "Baritone Sax",
    "68": "Oboe",
    "69": "English Horn",
    "70": "Bassoon",
    "71": "Clarinet",
    "72": "Piccolo",
    "73": "Flute",
    "74": "Recorder",
    "75": "Pan Flute",
    "76": "Bottle Blow",
    "77": "Shakuhachi",
    "78": "Whistle",
    "79": "Ocarina",
    "80": "Lead 1 (square)",
    "81": "Lead 2 (sawtooth)",
    "82": "Lead 3 (calliope)",
    "83": "Lead 4 (chiff)",
    "84": "Lead 5 (charang)",
    "85": "Lead 6 (voice)",
    "86": "Lead 7 (fifths)",
    "87": "Lead 8 (bass+lead)",
    "88": "Pad 1 (new age)",
    "89": "Pad 2 (warm)",
    "90": "Pad 3 (polysynth)",
    "91": "Pad 4 (choir)",
    "92": "Pad 5 (bowed)",
    "93": "Pad 6 (metallic)",
    "94": "Pad 7 (halo)",
    "95": "Pad 8 (sweep)",
    "96": "FX 1 (rain)",
    "97": "FX 2 (soundtrack)",
    "98": "FX 3 (crystal)",
    "99": "FX 4 (atmosphere)",
    "100": "FX 5 (brightness)",
    "101": "FX 6 (goblins)",
    "102": "FX 7 (echoes)",
    "103": "FX 8 (sci-fi)",
    "104": "Sitar",
    "105": "Banjo",
    "106": "Shamisen",
    "107": "Koto",
    "108": "Kalimba",
    "109": "Bagpipe",
    "110": "Fiddle",
    "111": "Shanai",
    "112": "Tinkle Bell",
    "113": "Agogo",
    "114": "Steel Drums",
    "115": "Woodblock",
    "116": "Taiko Drum",
    "117": "Melodic Tom",
    "118": "Synth Drum",
    "119": "Reverse Cymbal",
    "120": "Guitar Fret Noise",
    "121": "Breath Noise",
    "122": "Seashore",
    "123": "Bird Tweet",
    "124": "Telephone Ring",
    "125": "Helicopter",
    "126": "Applause",
    "127": "Gunshot",
    "128": "Percussion Instrument",
    "129": "Erhu",
    "130": "Zhonghu",
    "131": "Pipa",
    "132": "Gaohu",
    "133": "Suona",
    "134": "Dizi",
    "135": "Dauso",
    "136": "Xun",
    "137": "Yangqin",
    "138": "Xiao",
    "139": "Water Jean",
    "140": "Bright Guitar",
    "141": "Orchestra Piccolo",
    "142": "Heavy Metal Guitar",
    "143": "Crystal Guitar",
    "144": "Queer Electric Piano",
    "145": "Bright Bass",
    "146": "Rock Electric Bass",
    "147": "Psychedelic Bass",
    "148": "Rhythm Electric Bass",
    "149": "Heavy Metal Bass",
    "150": "Magic Electronic",
    "151": "Bright Violin",
    "152": "Ancient Violin",
    "153": "Heavy Bass Orchestra",
    "154": "Synth Clarinet",
    "155": "Interactive Lead",
    "156": "Orchestral Keyboard",
    "157": "Bagpipes",
    "158": "Synth Banjo",
    "159": "Japan Synth",
    "160": "Church Electric Piano",
    "161": "Synth Piano",
    "162": "Baritone Piano",
    "163": "String Piano",
    "164": "Metal Piano",
    "165": "Bright Rhythm Piano",
    "166": "Electric Piano Pad",
    "167": "Classical Piano",
    "168": "Organ Guitar",
    "169": "Electric Guitar",
    "170": "Synthesis Nylon Guitar",
    "171": "Synth Guitar",
    "172": "Bright Clean Guitar",
    "173": "Psychedelic Guitar",
    "174": "Orchestra Guitar",
    "175": "Funky Guitar",
    "176": "Electronic Guitar",
    "177": "Electronic Symphony",
    "178": "Synth Electronic Violin",
    "179": "Stringed Violin",
    "180": "String Violin",
    "181": "Electronic Violin",
    "182": "Electronic Orchestra",
    "183": "Pizzicato Violin",
    "184": "Pizzicato Ensemble 1",
    "185": "Pizzicato Ensemble 2",
    "186": "Baritone Synth Contrabass",
    "187": "Bass Flute",
    "188": "Distortion Contrabass",
    "189": "Contrabass Lead",
    "190": "Violin Lead",
    "191": "Cello Lead",
    "192": "Pizzicato Rhythm",
    "193": "High Harp",
    "194": "Harp Ensemble",
    "195": "Synth Harp"
  },
"CT-660": {
    "00": "Piano",
    "01": "Harpsichord",
    "02": "Vibraphone",
    "03": "Jazz Organ",
    "04": "Pipe Organ",
    "05": "Brass Ens",
    "06": "Flute",
    "07": "Chorus",
    "08": "Jazz Guitar",
    "09": "Bells",
    "10": "Funky Clavi",
    "11": "Metallic Sound",
    "12": "Synth-Ens",
    "13": "Percussion (Multi-Split)",
    "14": "Sound Effect 1 (Multi-Split)",
    "15": "Honky-Tonk Piano",
    "16": "Elec Piano",
    "17": "Marimba",
    "18": "Organ",
    "19": "Accordion",
    "20": "Strings",
    "21": "Oboe",
    "22": "Synth-Reed",
    "23": "Harp",
    "24": "Synth-Celesta",
    "25": "Synth-Clavi",
    "26": "Fantasy",
    "27": "Miracle",
    "28": "Bass (Multi-Split)",
    "29": "Sound Effect 2 (Multi-Split)"
  },
"QUADRAVERB": {
    "00": "EQ, CRS, DLY, +RVB",
    "01": "PR-EQ REVERB",
    "02": "POST EQ REVERB",
    "03": "GATED REVERB",
    "04": "STEREO CHORUS",
    "05": "STEREO FLANGE",
    "06": "PINGPONG DELAY",
    "07": "DETUNE +12",
    "08": "LAZY 'AFTERTOUCH'",
    "09": "5 BAND PARA EQ",
    "10": "SMALL ROOM",
    "11": "MED ROOM",
    "12": "LARGE ROOM",
    "13": "SMALL HALL",
    "14": "MEDIUM HALL",
    "15": "CONCERT 1",
    "16": "CONCERT 2",
    "17": "SML VOCAL PLATE",
    "18": "VOCAL PLATE",
    "19": "LG VOCAL PLATE",
    "20": "LO DISHED CHAMBER",
    "21": "RICH CHAMBER",
    "22": "KINGS CHAMBER",
    "23": "SML TIGHT GATE",
    "24": "BRITELITE GATE",
    "25": "SMOOTH GATE",
  "26": "MEAN GATE",
  "27": "GATE PLUS VERB",
  "28": "FLANGE/GATE",
  "29": "FLANGE/GATE 2",
  "30": "MONO FLANGE",
  "31": "TRIGGER FLANGE",
  "32": "TWITCH FLANGER",
  "33": "MONO CHORUS",
  "34": "CHORUS ROOM",
  "35": "CHORUS REVERB",
  "36": "CHORUS DELAY",
  "37": "STEREO PITCH",
  "38": "LOOSE LEZLIE",
  "39": "P BEND LEZLIE",
  "40": "167ms DELAY",
  "41": "250ms DELAY",
  "42": "500ms DELAY",
  "43": "1500ms DELAY",
  "44": "ECHO 2 THE LEFT",
  "45": "ECHO FLANGE",
  "46": "FLANGED ECHOES",
  "47": "FLANGED ECHO 2",
  "48": "REVERSE ECHO",
  "49": "PITCH REVERSE ECHO",
  "50": "RAD KICK",
    "51": "AMAZING BASS",
  "52": "BALLAD SNARE 1",
  "53": "BALLAD SNARE 2",
  "54": "WET RHY GTR",
  "55": "WET ECHO STRAT",
  "56": "SKANK GTR",
  "57": "LEAD GUITAR 1",
  "58": "LEAD GUITAR 2",
  "59": "GREASE GUITAR",
  "60": "CONCERT GUITAR",
  "61": "ACOUSTIC GTR",
  "62": "ROCK ACOUSTIC",
  "63": "CHORUS STRINGS 1",
  "64": "CHORUS STRINGS 2",
  "65": "ROADZ CHORUS +",
  "66": "HOLMES' PLATE",
  "67": "SUSPDELAY 1",
  "68": "STEREO SPREAD 1",
  "69": "STEREO SPREAD 2",
  "70": "DELAYED REVERB",
  "71": "DEEP SPACE ECHO",
  "72": "WONG WAY VERB",
  "73": "VERB SHIFTER",
  "74": "MULTI VOCAL",
  "75": "TAJ MAHAL MOD W",
  "76": "VELOCITY ECHO+",
  "77": "VELOCITY ECHO-",
  "78": "VELOCITY + REVERB",
  "79": "VELOCITY - REVERB",
  "80": "ROUGH TUBE !",
  "81": "ROUGH PIPE ! +",
  "82": "BEAM ME UP !!!",
  "83": "VERBATUM DELI",
  "84": "QUADREAMVERB",
  "85": "ELECTRIC BLUE!",
  "86": "DTUNE>SPRD>RVB",
  "87": "CHORUS>ECHO>RVB",
  "88": "FLANG>ECHO>RVB",
  "89": "DETUNEGATEVERB",
  "90": "BEATLY PLATE",
  "91": "SILENCE!",
  "92": "MED VOCALPLATE",
  "93": "LENNON VOCAL",
  "94": "Mellow Hall 1",
  "95": "BOXY ROOM",
  "96": "MENTAL FLANGE",
  "97": "Heavenly Hall",
  "98": "AMBIENT",
  "99": "GIGAREVERB VERB"
  }
}
    
